SnowflakeData.py
NikeCAQA-0.0.5.dist-info/LICENSE
NikeCAQA-0.0.5.dist-info/METADATA
NikeCAQA-0.0.5.dist-info/WHEEL
NikeCAQA-0.0.5.dist-info/top_level.txt
NikeCAQA-0.0.5.dist-info/RECORD
