Metadata-Version: 2.1
Name: NikeCAQA
Version: 0.0.5
Summary: Run Query on Snowflake!
Classifier: Programming Language :: Python :: 3
Classifier: Programming Language :: Python :: 3.11
Classifier: License :: OSI Approved :: GNU General Public License v2 or later (GPLv2+)
Classifier: Operating System :: OS Independent
License-File: LICENSE
Requires-Dist: asn1crypto (==1.5.1)
Requires-Dist: certifi (==2022.12.7)
Requires-Dist: cffi (==1.15.1)
Requires-Dist: charset-normalizer (==2.1.1)
Requires-Dist: cryptography (==39.0.1)
Requires-Dist: databricks (==0.2)
Requires-Dist: databricks-sql (==1.0.0)
Requires-Dist: databricks-sql-connector (==2.2.1)
Requires-Dist: filelock (==3.9.0)
Requires-Dist: gitdb (==4.0.10)
Requires-Dist: GitPython (==3.1.31)
Requires-Dist: greenlet (==2.0.2)
Requires-Dist: idna (==3.4)
Requires-Dist: lz4 (==4.3.2)
Requires-Dist: numpy (==1.23.4)
Requires-Dist: oauthlib (==3.2.2)
Requires-Dist: oscrypto (==1.3.0)
Requires-Dist: pandas (==1.5.3)
Requires-Dist: pyarrow (==10.0.1)
Requires-Dist: pycparser (==2.21)
Requires-Dist: pycryptodomex (==3.17)
Requires-Dist: PyJWT (==2.6.0)
Requires-Dist: pyOpenSSL (==23.0.0)
Requires-Dist: pystache (==0.6.0)
Requires-Dist: python-dateutil (==2.8.2)
Requires-Dist: pytz (==2022.7.1)
Requires-Dist: requests (==2.28.2)
Requires-Dist: six (==1.16.0)
Requires-Dist: smmap (==5.0.0)
Requires-Dist: snowflake-connector-python (==3.0.0)
Requires-Dist: snowflake-sqlalchemy (==1.4.6)
Requires-Dist: SQLAlchemy (==1.4.46)
Requires-Dist: thrift (==0.16.0)
Requires-Dist: typing-extensions (==4.5.0)
Requires-Dist: urllib3 (==1.26.14)
Requires-Dist: xcrun (==0.4)
Requires-Dist: wheel
Requires-Dist: configparser (~=5.3.0)
